{"references": [{"fullname_first_author": "Qi Wang", "paper_title": "A simple yet effective strategy to robustify the meta learning paradigm", "publication_date": "2023-12-31", "reason": "This paper is the most directly related work, and the current work builds upon and extends it."}, {"fullname_first_author": "Chelsea Finn", "paper_title": "Model-agnostic meta-learning for fast adaptation of deep networks", "publication_date": "2017-07-01", "reason": "This is a foundational paper in the field of meta-learning which is the basis for many other methods mentioned."}, {"fullname_first_author": "Marta Garnelo", "paper_title": "Conditional neural processes", "publication_date": "2018-07-01", "reason": "This paper introduces a core method used in meta-learning which is used as a comparison."}, {"fullname_first_author": "Liam Collins", "paper_title": "Task-robust model-agnostic meta-learning", "publication_date": "2020-12-31", "reason": "This paper introduces a key comparative approach to the current work."}, {"fullname_first_author": "R Tyrrell Rockafellar", "paper_title": "Optimization of conditional value-at-risk", "publication_date": "2000-12-31", "reason": "This paper introduces a core concept used in the current work."}]}